pypapagotranslate/LangDetect.py
pypapagotranslate/NameRoman.py
pypapagotranslate/Translate.py
pypapagotranslate/__init__.py
pypapagotranslate/api.py
pypapagotranslate/exceptions.py
pypapagotranslate/translator.py
pypapagotranslate-0.2.0.dist-info/LICENSE
pypapagotranslate-0.2.0.dist-info/METADATA
pypapagotranslate-0.2.0.dist-info/WHEEL
pypapagotranslate-0.2.0.dist-info/top_level.txt
pypapagotranslate-0.2.0.dist-info/RECORD
