Metadata-Version: 2.1
Name: pypapagotranslate
Version: 0.2.0
Summary: Papago Translate client for Python
Home-page: https://github.com/SeolHa314/pypapagotranslate
License: MIT
Keywords: papago translate wrapper n2mt smt
Platform: Windows
Platform: Linux
Platform: OSX
Classifier: Development Status :: 3 - Alpha
Classifier: License :: OSI Approved :: MIT License
Classifier: Programming Language :: Python :: 3.5
Classifier: Programming Language :: Python :: 3.6
Classifier: Programming Language :: Python :: 3.7
Classifier: Programming Language :: Python :: 3 :: Only
Classifier: Programming Language :: Python :: Implementation :: CPython
Classifier: Topic :: Text Processing :: Linguistic
Classifier: Intended Audience :: Developers
Requires-Python: >=3.5
Requires-Dist: requests
